grabfeed/__init__.py
grabfeed/grabber.py
grabfeed-0.3.1.dist-info/DESCRIPTION.rst
grabfeed-0.3.1.dist-info/METADATA
grabfeed-0.3.1.dist-info/RECORD
grabfeed-0.3.1.dist-info/WHEEL
grabfeed-0.3.1.dist-info/metadata.json
grabfeed-0.3.1.dist-info/top_level.txt
