Metadata-Version: 2.0
Name: grabfeed
Version: 0.3.1
Summary: Detects and return RSS feeds for a given website.
Home-page: https://github.com/kaflesudip/grabfeed
Author: Sudip Kafle
Author-email: soodip.kafle@gmail.com
License: UNKNOWN
Download-URL: https://github.com/kaflesudip/grabfeed/tarball/0.3.1
Keywords: RSS,Feeds,Scraping
Platform: UNKNOWN
Requires-Dist: beautifulsoup4 (==4.4.1)
Requires-Dist: requests (==2.8.1)
